v4l2.py
v4l2_python3-0.3.4.dist-info/AUTHORS
v4l2_python3-0.3.4.dist-info/LICENSE
v4l2_python3-0.3.4.dist-info/METADATA
v4l2_python3-0.3.4.dist-info/WHEEL
v4l2_python3-0.3.4.dist-info/top_level.txt
v4l2_python3-0.3.4.dist-info/RECORD
